odoo/addons/sale_stock_release_channel_delivery/README.rst
odoo/addons/sale_stock_release_channel_delivery/__init__.py
odoo/addons/sale_stock_release_channel_delivery/__manifest__.py
odoo/addons/sale_stock_release_channel_delivery/i18n/it.po
odoo/addons/sale_stock_release_channel_delivery/i18n/sale_stock_release_channel_delivery.pot
odoo/addons/sale_stock_release_channel_delivery/models/__init__.py
odoo/addons/sale_stock_release_channel_delivery/models/sale_order.py
odoo/addons/sale_stock_release_channel_delivery/readme/CONTRIBUTORS.md
odoo/addons/sale_stock_release_channel_delivery/readme/DESCRIPTION.md
odoo/addons/sale_stock_release_channel_delivery/static/description/icon.png
odoo/addons/sale_stock_release_channel_delivery/static/description/index.html
odoo/addons/sale_stock_release_channel_delivery/tests/__init__.py
odoo/addons/sale_stock_release_channel_delivery/tests/test_release_channel.py
odoo_addon_sale_stock_release_channel_delivery-18.0.1.0.0.2.dist-info/METADATA
odoo_addon_sale_stock_release_channel_delivery-18.0.1.0.0.2.dist-info/WHEEL
odoo_addon_sale_stock_release_channel_delivery-18.0.1.0.0.2.dist-info/top_level.txt
odoo_addon_sale_stock_release_channel_delivery-18.0.1.0.0.2.dist-info/RECORD
